{
  "symbol": "SPX",
  "decision_timeframe": "30 mins",
  "net_modeled_pnl": -4958.4,
  "net_dollar_pnl": -495840.0,
  "return_on_capital": -4.9584,
  "max_gross_deployment_dollars": 9916.8,
  "worst_day_pnl_dollars": -9916.8,
  "worst_week_pnl_dollars": -9916.8,
  "profit_factor_by_closed_layer": 0.0,
  "profit_factor_by_week": 0.0,
  "weekly_occupancy_rate": 0.0,
  "avg_adjustments_per_week": 0.0,
  "weeks_traded": 50,
  "weeks_aborted": 15,
  "max_active_butterflies": 3,
  "closed_layers": 150,
  "winning_layers": 0,
  "losing_layers": 150,
  "metric_definitions": {
    "net_modeled_pnl": "Final modeled weekly corridor equity in model points after friction.",
    "net_dollar_pnl": "net_modeled_pnl * option_multiplier * contracts_per_layer.",
    "return_on_capital": "net_dollar_pnl / starting_capital.",
    "max_gross_deployment_dollars": "Peak active layer entry cost sum converted to dollars.",
    "worst_day_pnl_dollars": "Minimum grouped daily bar_pnl converted to dollars.",
    "worst_week_pnl_dollars": "Minimum grouped week bar_pnl converted to dollars.",
    "profit_factor_by_closed_layer": "Gross winner realized_pnl divided by absolute gross loser realized_pnl.",
    "profit_factor_by_week": "Gross positive weekly modeled pnl divided by absolute gross negative weekly modeled pnl.",
    "weekly_occupancy_rate": "Share of bars where price stayed inside the active butterfly corridor span.",
    "avg_adjustments_per_week": "ADD_ADJUSTMENT action count / weeks_traded.",
    "weeks_traded": "Distinct week_key count with DEPLOY_INITIAL actions.",
    "weeks_aborted": "Distinct week_key count with ABORT actions.",
    "max_active_butterflies": "Maximum concurrent active weekly butterflies observed in the equity curve."
  }
}